mppfc/__init__.py
mppfc/cache.py
mppfc/mppfc.py
mppfc-1.1.2.dist-info/WHEEL
mppfc-1.1.2.dist-info/METADATA
mppfc-1.1.2.dist-info/LICENSE
mppfc-1.1.2.dist-info/RECORD
