Metadata-Version: 2.1
Name: mppfc
Version: 1.1.2
Summary: multi-processing persistent function cache
License: MIT
Author: Richard Hartmann
Author-email: richard_hartmann@gmx.de
Requires-Python: >=3.8,<4.0
Classifier: License :: OSI Approved :: MIT License
Classifier: Programming Language :: Python :: 3
Classifier: Programming Language :: Python :: 3.8
Classifier: Programming Language :: Python :: 3.9
Classifier: Programming Language :: Python :: 3.10
Classifier: Programming Language :: Python :: 3.11
Classifier: Programming Language :: Python :: 3
Classifier: Topic :: Scientific/Engineering
Requires-Dist: binfootprint (>=1.0.0,<2.0.0)
